{
  "id": "mock-doc-id",
  "url": null,
  "type": "quadros_adesivados",
  "href": null,
  "tags": [],
  "first_publication_date": "1970-01-01T00:00:01+0000",
  "last_publication_date": "1970-01-01T00:00:01+0000",
  "slugs": [],
  "linked_documents": [],
  "lang": "en-us",
  "alternate_languages": [],
  "data": {
    "title": "medicine",
    "author": "thought",
    "banner": {
      "dimensions": {
        "width": 900,
        "height": 500
      },
      "alt": null,
      "copyright": null,
      "url": "https://images.unsplash.com/photo-1494438639946-1ebd1d20bf85"
    },
    "price": 64,
    "content": [
      {
        "heading": "care",
        "body": [
          {
            "type": "paragraph",
            "text": "Laborum fugiat id aliqua dolore in sint culpa officia enim cillum mollit ut. Dolor commodo sint aliquip aliqua aliqua consequat in proident aute pariatur sunt voluptate. Tempor exercitation adipisicing magna deserunt.",
            "spans": []
          }
        ]
      }
    ]
  }
}